surrealengine/__init__.py
surrealengine/aggregation.py
surrealengine/base_query.py
surrealengine/connection.py
surrealengine/datagrid_api.py
surrealengine/document.py
surrealengine/events.py
surrealengine/exceptions.py
surrealengine/expr.py
surrealengine/graph.py
surrealengine/logging.py
surrealengine/materialized_view.py
surrealengine/meta.py
surrealengine/pagination.py
surrealengine/query_expressions.py
surrealengine/record_id_utils.py
surrealengine/relation_update.py
surrealengine/schema.py
surrealengine/schemaless.py
surrealengine/signals.py
surrealengine/surrealql.py
surrealengine/fields/__init__.py
surrealengine/fields/additional.py
surrealengine/fields/base.py
surrealengine/fields/collection.py
surrealengine/fields/datetime.py
surrealengine/fields/geometry.py
surrealengine/fields/id.py
surrealengine/fields/reference.py
surrealengine/fields/scalar.py
surrealengine/fields/specialized.py
surrealengine/query/__init__.py
surrealengine/query/base.py
surrealengine/query/descriptor.py
surrealengine/query/relation.py
surrealengine-0.6.0.dist-info/licenses/LICENSE
surrealengine-0.6.0.dist-info/METADATA
surrealengine-0.6.0.dist-info/WHEEL
surrealengine-0.6.0.dist-info/top_level.txt
surrealengine-0.6.0.dist-info/RECORD
