Metadata-Version: 2.4
Name: surrealengine
Version: 0.6.0
Summary: An async Object-Document Mapper (ODM) for SurrealDB
Author: Iristech Systems
License: MIT License
Project-URL: Homepage, https://github.com/iristech-systems/surrealengine
Project-URL: Bug Tracker, https://github.com/iristech-systems/surrealengine/issues
Keywords: surrealdb,odm,database,async,orm
Classifier: Development Status :: 4 - Beta
Classifier: Intended Audience :: Developers
Classifier: License :: OSI Approved :: MIT License
Classifier: Programming Language :: Python :: 3
Classifier: Programming Language :: Python :: 3.10
Classifier: Programming Language :: Python :: 3.11
Classifier: Topic :: Database
Classifier: Topic :: Software Development :: Libraries :: Python Modules
Classifier: Framework :: AsyncIO
Requires-Python: >=3.10
License-File: LICENSE
Requires-Dist: aiohttp>=3.12.15
Requires-Dist: attrs==25.3.0
Requires-Dist: certifi==2025.8.3
Requires-Dist: charset-normalizer==3.4.3
Requires-Dist: docutils==0.22
Requires-Dist: frozenlist==1.7.0
Requires-Dist: marshmallow==4.0.0
Requires-Dist: multidict==6.6.4
Requires-Dist: propcache==0.3.2
Requires-Dist: pytz==2025.2
Requires-Dist: requests==2.32.5
Requires-Dist: surrealdb>=1.0.7
Requires-Dist: typing-extensions==4.15.0
Requires-Dist: websockets==15.0.1
Requires-Dist: yarl==1.20.1
Provides-Extra: signals
Requires-Dist: blinker>=1.6.2; extra == "signals"
Provides-Extra: jupyter
Requires-Dist: notebook==7.2.2; extra == "jupyter"
Provides-Extra: all
Requires-Dist: blinker>=1.6.2; extra == "all"
Requires-Dist: notebook==7.2.2; extra == "all"
Dynamic: license-file
